{
    "src":    "instruments/EGT.svg",

    "animations": [
      {
        "element": "#Needle",
        "type":    "transform",
        "transforms": [{
          "type": "rotate",
          "a": {
            "property": "egt",
            "scale": 122
          },
          "x": 256,
          "y": 369
        }]
      },
      {
        "element": "#HelperNeedle",
        "type":    "transform",
        "transforms": [{
          "type": "rotate",
          "a": {
            "property": "egtBug",
            "scale": 122
          },
          "x": 256,
          "y": 369
        }]
      }
    ]
}
